README.md
exemplo.py
setup.cfg
setup.py
NLPyPort/FullPipeline.py
NLPyPort/FullPipeline_anterior.py
NLPyPort/__init__.py
NLPyPort/text.py
NLPyPort.egg-info/PKG-INFO
NLPyPort.egg-info/SOURCES.txt
NLPyPort.egg-info/dependency_links.txt
NLPyPort.egg-info/requires.txt
NLPyPort.egg-info/top_level.txt
NLPyPort/CRF/CRF_NP_Final.py
NLPyPort/CRF/CRF_Teste.py
NLPyPort/CRF/NP_Final.pickle
NLPyPort/CRF/NP_Final_Macro.pickle
NLPyPort/CRF/__init__.py
NLPyPort/CRF/get-pip.py
NLPyPort/CRF/trainedModels/harem.pickle
NLPyPort/LemPyPort/LemFunctions.py
NLPyPort/LemPyPort/__init__.py
NLPyPort/LemPyPort/dictionary/dictionary.py
NLPyPort/LemPyPort/dictionary/dictionary_entry.py
NLPyPort/LemPyPort/normalization/__init__.py
NLPyPort/LemPyPort/normalization/adverb_normalizer.py
NLPyPort/LemPyPort/normalization/augmentative_normalizer.py
NLPyPort/LemPyPort/normalization/diminutive_normalizer.py
NLPyPort/LemPyPort/normalization/gender_name_normalizer.py
NLPyPort/LemPyPort/normalization/gender_normalizer.py
NLPyPort/LemPyPort/normalization/number_normalizer.py
NLPyPort/LemPyPort/normalization/superlative_normalizer.py
NLPyPort/LemPyPort/normalization/verb_normalizer.py
NLPyPort/LemPyPort/rank/word_ranking.py
NLPyPort/LemPyPort/resources/acdc/formas.total.txt
NLPyPort/LemPyPort/resources/acdc/lemas.total.txt
NLPyPort/LemPyPort/resources/config/lemport.properties
NLPyPort/LemPyPort/resources/dictionaries/custom.dic
NLPyPort/LemPyPort/resources/label/Label-Delaf_pt_v4_1.dic
NLPyPort/LemPyPort/resources/label/Label-Lex-notation.pdf
NLPyPort/LemPyPort/resources/label/Label-Lex_Description.pdf
NLPyPort/LemPyPort/resources/label/gpl-3.0-standalone.html
NLPyPort/LemPyPort/resources/label/gpl-3.0.pdf
NLPyPort/LemPyPort/resources/replacements/abbreviations.xml
NLPyPort/LemPyPort/resources/replacements/adverbdeclensions.xml
NLPyPort/LemPyPort/resources/replacements/augmentativedeclensions.xml
NLPyPort/LemPyPort/resources/replacements/clitics.xml
NLPyPort/LemPyPort/resources/replacements/contractions.xml
NLPyPort/LemPyPort/resources/replacements/diminutivedeclensions.xml
NLPyPort/LemPyPort/resources/replacements/genderdeclensions.xml
