Metadata-Version: 2.1
Name: NLPyPort
Version: 2.2.5
Summary: Python NLP for Portuguese
Home-page: https://github.com/jdportugal/NLPyPort
Author: Joao Ferreira
Author-email: jdhtml5@gmail.com
License: cc0-1.0
Download-URL: https://github.com/jdportugal/NLPyPort
Keywords: NLP,PORTUGUESE,PYTHON
Platform: UNKNOWN
Classifier: Development Status :: 4 - Beta
Classifier: Intended Audience :: Developers
Classifier: Topic :: Software Development :: Build Tools
Classifier: License :: OSI Approved :: MIT License
Classifier: Programming Language :: Python :: 3
Classifier: Programming Language :: Python :: 3.4
Classifier: Programming Language :: Python :: 3.5
Classifier: Programming Language :: Python :: 3.6
